{
  "stage": "published",
  "pipeline": "digest",
  "source": {
    "title": "DRAM prices to surge up to 70% in Q2 2026 as AI-driven memory shortage deepens",
    "url": "https://www.digitimes.com/news/a20260309VL200/digitimes-asia-weekly-news-roundup-tsmc-investigation-memory-price.html",
    "source_name": "DigiTimes Asia",
    "language": "en",
    "relevance_score": 88,
    "summary": "AI-driven data center expansion has pushed the memory market into a structural shortage, with DRAM prices expected to surge up to 70% in Q2 2026. Samsung Electronics and SK Hynix have notified customers of price increases, with the spot-contract price gap widening to 40-50%. The shortage reflects surging demand for HBM (High Bandwidth Memory) for AI chips that has pushed the market beyond traditional supply-demand cycles.",
    "published_date": "2026-03-09",
    "collected_at": "2026-03-09T15:02:00+09:00"
  },
  "digest": {
    "headline": "AI 수요 폭증에 DRAM 가격 최대 70% 급등 전망, 구조적 메모리 부족 심화",
    "lead": "AI 데이터센터 확장이 메모리 시장을 구조적 공급 부족으로 몰아넣으며, 2026년 2분기 DRAM 가격이 최대 70% 급등할 전망이다. 삼성전자와 SK하이닉스가 고객사에 가격 인상을 통보했으며, 현물-계약 가격 격차가 40~50%까지 벌어졌다.",
    "html": "<!--kg-card-begin: html-->\n<div style=\"font-family:'Noto Sans KR',Apple SD Gothic Neo,sans-serif;max-width:680px;margin:0 auto;color:#1a1a2e;font-size:17px;line-height:1.9;\">\n\n  <!-- 다이제스트 배지 (오렌지) -->\n  <div style=\"margin-bottom:28px;\">\n    <span style=\"display:inline-flex;align-items:center;gap:6px;background:#fff4ee;border:1px solid #fed7aa;padding:4px 12px;border-radius:20px;font-size:13px;color:#c2410c;font-weight:500;\">\n      ⚡ AI Digest\n    </span>\n  </div>\n\n  <!-- 리드 박스 -->\n  <div style=\"border-left:4px solid #FF6B35;padding:16px 20px;background:#fff9f6;border-radius:0 8px 8px 0;margin-bottom:40px;\">\n    <p style=\"margin:0;font-size:17px;line-height:1.85;color:#1a1a2e;\">AI 데이터센터 확장이 메모리 시장을 구조적 공급 부족으로 몰아넣으며, 2026년 2분기 DRAM 가격이 최대 70% 급등할 전망이다. 삼성전자와 SK하이닉스가 고객사에 가격 인상을 통보했으며, 현물-계약 가격 격차가 40~50%까지 벌어졌다.</p>\n  </div>\n\n  <!-- 본문 섹션 -->\n  <h2 style=\"font-size:18px;font-weight:700;color:#111;border-bottom:1px solid #e2e8f0;padding-bottom:8px;margin:36px 0 16px;\">배경</h2>\n  <p style=\"margin:0 0 28px;\">AI 칩용 HBM(고대역폭 메모리) 수요가 폭발적으로 증가하면서 메모리 시장이 전통적인 수급 사이클을 벗어났다. 엔비디아 GTC 2026 이후 AI 메모리 랠리가 본격화됐으며, 삼성전자와 SK하이닉스는 2분기부터 연속적인 계약 가격 인상에 나섰다. 현물 가격이 계약 가격을 크게 앞지르면서 메모리 공급업체들의 가격 협상력이 더욱 강화되는 양상이다.</p>\n\n  <h2 style=\"font-size:18px;font-weight:700;color:#111;border-bottom:1px solid #e2e8f0;padding-bottom:8px;margin:36px 0 16px;\">의미와 전망</h2>\n  <p style=\"margin:0 0 28px;\">이번 가격 급등은 단순한 시장 변동이 아닌 AI 인프라 확장에 따른 구조적 전환을 반영한다. 대형 구매자에게 유리한 거래 관행이 자리 잡으면서 중소 IT 기업과 서버 제조사의 비용 부담이 가중될 전망이다. 미국의 중국산 반도체 연방 조달 금지 조치까지 겹치면서 글로벌 전자 공급망의 긴장이 더욱 고조되고 있다.</p>\n\n  <!-- 에듀테크 시사점 (필수) -->\n  <h2 style=\"font-size:18px;font-weight:700;color:#FF6B35;border-bottom:1px solid #fed7aa;padding-bottom:8px;margin:36px 0 16px;\">🎓 에듀테크 시사점</h2>\n  <p style=\"margin:0 0 28px;\">DRAM 가격 급등은 AI 학습 플랫폼 운영에 필요한 GPU 서버 및 클라우드 인프라 비용 상승으로 직결된다. 에듀테크 기업들이 AI 기반 개인화 학습·자동 평가 시스템을 확장하려 할 때 인프라 비용 부담이 커질 수 있으며, 비용 최적화를 위한 경량 모델 도입과 온디바이스 추론 전략이 더욱 중요해질 것이다.</p>\n\n  <!-- 원문 출처 -->\n  <div style=\"margin-top:36px;padding:14px 18px;background:#f8fafc;border-radius:8px;border:1px solid #e2e8f0;\">\n    <p style=\"margin:0;font-size:14px;color:#64748b;\">📎 원문: <a href=\"https://www.digitimes.com/news/a20260309VL200/digitimes-asia-weekly-news-roundup-tsmc-investigation-memory-price.html\" style=\"color:#FF6B35;text-decoration:none;\">DigiTimes Asia</a></p>\n  </div>\n\n  <!-- AI 각주 -->\n  <p style=\"margin:28px 0 0;padding-top:14px;border-top:1px solid #f1f5f9;font-size:13px;color:#cbd5e1;\">본 기사는 AI가 작성했습니다 (AI 기본법 제31조)</p>\n\n</div>\n<!--kg-card-end: html-->",
    "ghost_tags": [
      "ai-digest",
      "ai",
      "technology",
      "samsung"
    ],
    "meta_title": "AI 수요 폭증으로 2분기 DRAM 가격 최대 70% 급등 전망",
    "meta_description": "AI 데이터센터 확장으로 메모리 시장이 구조적 부족에 빠졌다. 삼성전자·SK하이닉스가 DRAM 가격 인상을 통보, 2분기 최대 70% 급등이 예상된다.",
    "word_count": 510
  },
  "audit_log": [
    {
      "agent": "digest-collector",
      "action": "sourced",
      "timestamp": "2026-03-09T15:02:00+09:00"
    },
    {
      "agent": "digest-writer",
      "action": "drafted",
      "timestamp": "2026-03-09T15:15:00+09:00"
    },
    {
      "agent": "digest-publisher",
      "action": "published",
      "timestamp": "2026-03-09T06:30:59.643Z"
    }
  ],
  "publish_result": {
    "ghost_post_id": "69ae6923ff4fbf0001ab7857",
    "ghost_url": "https://ubion.ghost.io/ghost/#/editor/post/69ae6923ff4fbf0001ab7857",
    "public_url": "https://insight.ubion.global/ai-suyo-pogjeunge-dram-gagyeog-coedae-70-geubdeung-jeonmang-gujojeog-memori-bujog-simhwa/",
    "status": "published",
    "published_at": "2026-03-09T06:30:59.000Z"
  }
}